cis_checks_2023_u1_3/__init__.py
cis_checks_2023_u1_3/_security_control_5.py
cis_checks_2023_u1_3/iam_control_1.py
cis_checks_2023_u1_3/logging_control_3.py
cis_checks_2023_u1_3/monitoring_control_4.py
cis_checks_2023_u1_3/networking_control_5.py
cis_checks_2023_u1_3/storage_control_2.py
cis_checks_2023_u1_3/utils.py
cis_checks_2023_u1_3-2.1.3.dist-info/METADATA
cis_checks_2023_u1_3-2.1.3.dist-info/WHEEL
cis_checks_2023_u1_3-2.1.3.dist-info/top_level.txt
cis_checks_2023_u1_3-2.1.3.dist-info/RECORD
