Metadata-Version: 2.1
Name: cis-checks-2023-u1-3
Version: 2.1.3
Summary: Provides AWS compliance details
Author: Dheeraj Banodha, Ravish Sharma
Classifier: Programming Language :: Python :: 3
Classifier: Operating System :: OS Independent
Requires-Python: >=3.7
Requires-Dist: boto3
Requires-Dist: pytz
